LICENSE.txt
README.txt
setup.cfg
setup.py
docs/HISTORY.txt
zopyx/__init__.py
zopyx.smartprintng.client.egg-info/PKG-INFO
zopyx.smartprintng.client.egg-info/SOURCES.txt
zopyx.smartprintng.client.egg-info/dependency_links.txt
zopyx.smartprintng.client.egg-info/entry_points.txt
zopyx.smartprintng.client.egg-info/namespace_packages.txt
zopyx.smartprintng.client.egg-info/not-zip-safe
zopyx.smartprintng.client.egg-info/requires.txt
zopyx.smartprintng.client.egg-info/top_level.txt
zopyx/smartprintng/__init__.py
zopyx/smartprintng/client/__init__.py
zopyx/smartprintng/client/header.txt
zopyx/smartprintng/client/zip_client.py
zopyx/smartprintng/client/test_data/test.html
zopyx/smartprintng/client/test_data/test.jpg