Metadata-Version: 1.0
Name: zopyx.smartprintng.client
Version: 0.8.3
Summary: ZOPYX SmartPrintNG Client Library
Home-page: http://pypi.python.org/pypi/zopyx.smartprintng.client
Author: Andreas Jung
Author-email: info@zopyx.com
License: ZPL
Keywords: Produce Publish Python Zope Plone PDF
Platform: UNKNOWN
Classifier: Programming Language :: Python
Classifier: Topic :: Software Development :: Libraries :: Python Modules
